ve/__init__.py
ve/__main__.py
ve/_core.py
ve/_i18n.py
ve/_meta.py
ve/cli.py
ve-0.0.1.dist-info/LICENSE.txt
ve-0.0.1.dist-info/METADATA
ve-0.0.1.dist-info/WHEEL
ve-0.0.1.dist-info/entry_points.txt
ve-0.0.1.dist-info/top_level.txt
ve-0.0.1.dist-info/RECORD
