Metadata-Version: 2.1
Name: ve
Version: 0.0.1
Summary: ve application
Home-page: https://pypi.org/project/ve/
Author: sinoroc
Author-email: sinoroc.code+python@gmail.com
License: Apache-2.0
Project-URL: GitLab, https://gitlab.com/sinoroc/ve
Project-URL: GitHub, https://github.com/sinoroc/ve
Platform: UNKNOWN
Requires-Dist: importlib-metadata
Provides-Extra: package
Requires-Dist: twine ; extra == 'package'
Requires-Dist: wheel ; extra == 'package'
Requires-Dist: zapp ; extra == 'package'
Provides-Extra: test
Requires-Dist: pytest ; extra == 'test'
Requires-Dist: pytest-pycodestyle ; extra == 'test'
Requires-Dist: pytest-pylint ; extra == 'test'
